{
    "ticker": "sats",
    "holdersCount": 46549,
    "historyCount": 21645068,
    "inscriptionNumber": 357097,
    "inscriptionId": "9b664bdd6f5ed80d8d88957b63364c41f3ad4efb8eee11366aa16435974d9333i0",
    "max": "2100000000000000",
    "limit": "100000000",
    "minted": "2100000000000000",
    "totalMinted": "2100000000000000",
    "confirmedMinted": "2100000000000000",
    "confirmedMinted1h": "2100000000000000",
    "confirmedMinted24h": "2100000000000000",
    "mintTimes": 21010783,
    "decimal": 18,
    "creator": "bc1prtawdt82wfgrujx6d0heu0smxt4yykq440t447wan88csf3mc7csm3ulcn",
    "txid": "9b664bdd6f5ed80d8d88957b63364c41f3ad4efb8eee11366aa16435974d9333",
    "deployHeight": 779971,
    "deployBlocktime": 1678339934,
    "completeHeight": 809135,
    "completeBlocktime": 1695552732,
    "inscriptionNumberStart": 357097,
    "inscriptionNumberEnd": 34539796
}